startpage.py
startpage_python-1.0.0.dist-info/LICENSE
startpage_python-1.0.0.dist-info/METADATA
startpage_python-1.0.0.dist-info/WHEEL
startpage_python-1.0.0.dist-info/top_level.txt
startpage_python-1.0.0.dist-info/RECORD
