Metadata-Version: 2.1
Name: startpage-python
Version: 1.0.0
Summary: performing websearch via startpage search engine (based on google.com)
Home-page: https://github.com/mohamedkasem99/startpage-python
License: GPL-3.0 License
Requires-Python: >=3.6
License-File: LICENSE
Requires-Dist: requests (==2.28.1)
Requires-Dist: beautifulsoup4 (==4.9.3)
